{"nodes": [{"id": "lib_faceapi_js", "label": "faceApi.js", "file_type": "code", "source_file": "lib\\faceApi.js", "source_location": "L1"}, {"id": "faceapi_configuretensorflow", "label": "configureTensorflow()", "file_type": "code", "source_file": "lib\\faceApi.js", "source_location": "L15"}, {"id": "faceapi_loadfaceapimodels", "label": "loadFaceApiModels()", "file_type": "code", "source_file": "lib\\faceApi.js", "source_location": "L31"}, {"id": "faceapi_detectdominantemotion", "label": "detectDominantEmotion()", "file_type": "code", "source_file": "lib\\faceApi.js", "source_location": "L56"}], "edges": [{"source": "lib_faceapi_js", "target": "faceapi_configuretensorflow", "relation": "contains", "confidence": "EXTRACTED", "source_file": "lib\\faceApi.js", "source_location": "L15", "weight": 1.0}, {"source": "lib_faceapi_js", "target": "faceapi_loadfaceapimodels", "relation": "contains", "confidence": "EXTRACTED", "source_file": "lib\\faceApi.js", "source_location": "L31", "weight": 1.0}, {"source": "lib_faceapi_js", "target": "faceapi_detectdominantemotion", "relation": "contains", "confidence": "EXTRACTED", "source_file": "lib\\faceApi.js", "source_location": "L56", "weight": 1.0}, {"source": "faceapi_detectdominantemotion", "target": "faceapi_loadfaceapimodels", "relation": "calls", "confidence": "EXTRACTED", "source_file": "lib\\faceApi.js", "source_location": "L57", "weight": 1.0}]}